{
	"dialogue": [
		{
			"expression": "talk",
			"text": "...",
			"boxState": "normal",
			"portrait": "bf",
			"speed": 0.05
		},
		{
			"expression": "confused",
			"text": "Whoa... that was intense. This virtual world is more impressive than I thought.",
			"boxState": "normal",
			"portrait": "bf",
			"speed": 0.05
		},
		{
			"expression": "excited",
			"text": "I would enjoy this place a whole lot more if I wasn’t trapped here against my will..",
			"boxState": "normal",
			"portrait": "bf",
			"speed": 0.05
		},
		{
			"expression": "talk",
			"text": "*pops into existence*",
			"boxState": "normal",
			"portrait": "gf",
			"speed": 0.05
		},
		{
			"expression": "confused",
			"text": "Welcome to Strawberry House. Here, you will face your third challenger.",
			"boxState": "normal",
			"portrait": "gf",
			"speed": 0.05
		},
		{
			"expression": "talk",
			"text": "Alrighty then... who’s next on the list?",
			"boxState": "normal",
			"portrait": "bf",
			"speed": 0.05
		},
		{
			"expression": "talk",
			"text": "That would be me, Mr. Saihara.",
			"boxState": "normal",
			"portrait": "gundham",
			"speed": 0.05
		},
		{
			"expression": "pissed",
			"text": "FINALLY! Someone got my damn name right!",
			"boxState": "normal",
			"portrait": "bf",
			"speed": 0.05
		},
		{
			"expression": "talk",
			"text": "There he is... Gundham Tanaka, the Ultimate Breeder.",
			"boxState": "normal",
			"portrait": "gf",
			"speed": 0.05
		},
		{
			"expression": "shocked",
			"text": "The Ultimate WHAT?!",
			"boxState": "normal",
			"portrait": "bf",
			"speed": 0.05
		},
		{
			"expression": "shocked",
			"text": "He’s an animal breeder, calm down.",
			"boxState": "normal",
			"portrait": "gf",
			"speed": 0.05
		},
		{
			"expression": "talk",
			"text": "Look, let’s just get this over with.",
			"boxState": "normal",
			"portrait": "bf",
			"speed": 0.05
		},
		{
			"expression": "excited",
			"text": "My, aren’t we impatient? Very well...\n I accept your challenge!",
			"boxState": "normal",
			"portrait": "gundham",
			"speed": 0.05
		}
	]
}